pytest_splunk_env/Dockerfile.splunk
pytest_splunk_env/__init__.py
pytest_splunk_env/sc4s/__init__.py
pytest_splunk_env/sc4s/base.py
pytest_splunk_env/sc4s/dockercompose.py
pytest_splunk_env/sc4s/external.py
pytest_splunk_env/splunk/__init__.py
pytest_splunk_env/splunk/base.py
pytest_splunk_env/splunk/docker.py
pytest_splunk_env/splunk/dockercompose.py
pytest_splunk_env/splunk/external.py
pytest_splunk_env/splunk/helmut/__init__.py
pytest_splunk_env/splunk/helmut/app/__init__.py
pytest_splunk_env/splunk/helmut/connector/__init__.py
pytest_splunk_env/splunk/helmut/connector/base.py
pytest_splunk_env/splunk/helmut/connector/httplib2_handler.py
pytest_splunk_env/splunk/helmut/connector/rest.py
pytest_splunk_env/splunk/helmut/connector/sdk.py
pytest_splunk_env/splunk/helmut/exceptions/__init__.py
pytest_splunk_env/splunk/helmut/exceptions/command_execution.py
pytest_splunk_env/splunk/helmut/exceptions/confs.py
pytest_splunk_env/splunk/helmut/exceptions/search.py
pytest_splunk_env/splunk/helmut/exceptions/wait.py
pytest_splunk_env/splunk/helmut/log/__init__.py
pytest_splunk_env/splunk/helmut/log/logging.conf
pytest_splunk_env/splunk/helmut/manager/__init__.py
pytest_splunk_env/splunk/helmut/manager/confs/__init__.py
pytest_splunk_env/splunk/helmut/manager/confs/conf.py
pytest_splunk_env/splunk/helmut/manager/confs/rest/__init__.py
pytest_splunk_env/splunk/helmut/manager/confs/rest/conf.py
pytest_splunk_env/splunk/helmut/manager/confs/rest/stanza.py
pytest_splunk_env/splunk/helmut/manager/confs/sdk/__init__.py
pytest_splunk_env/splunk/helmut/manager/confs/sdk/conf.py
pytest_splunk_env/splunk/helmut/manager/confs/sdk/stanza.py
pytest_splunk_env/splunk/helmut/manager/confs/stanza.py
pytest_splunk_env/splunk/helmut/manager/indexes/__init__.py
pytest_splunk_env/splunk/helmut/manager/indexes/index.py
pytest_splunk_env/splunk/helmut/manager/indexes/rest/__init__.py
pytest_splunk_env/splunk/helmut/manager/indexes/rest/index.py
pytest_splunk_env-0.1.2.dist-info/entry_points.txt
pytest_splunk_env-0.1.2.dist-info/LICENSES/Apache-2.0.txt
pytest_splunk_env-0.1.2.dist-info/WHEEL
pytest_splunk_env-0.1.2.dist-info/METADATA
pytest_splunk_env-0.1.2.dist-info/RECORD
